[
{"link": "/brow-wiz-pencil?productId=xlsImpprod840088"},
{"link": "/voluminous-lash-paradise-mascara?productId=xlsImpprod16151007"},
{"link": "/complexion-rescue-tinted-hydrating-gel-cream-broad-spectrum-spf-30?productId=xlsImpprod11771035"},
{"link": "/gimme-brow-volumizing-fiber-gel?productId=xlsImpprod14191015"},
{"link": "/monsieur-big-mascara?productId=xlsImpprod15891587"},
{"link": "/powermatte-lip-pigment?productId=xlsImpprod16671161"},
{"link": "/soft-matte-complete-concealer?productId=xlsImpprod15692183"},
{"link": "/duo-brush-12?productId=xlsImpprod6330248"},
{"link": "/naked-ultimate-basics?productId=xlsImpprod14791035"},
{"link": "/hydro-boost-hydrating-tint?productId=xlsImpprod15361057"},
{"link": "/megalast-metallic-liquid-catsuit?productId=xlsImpprod16691009"},
{"link": "/tarteist-pro-lash-adhesive?productId=xlsImpprod14291035"},
{"link": "/plush-rush-lipstick?productId=xlsImpprod13561043"},
{"link": "/slant-tweezer?productId=prod2041233"},
{"link": "/intense-therapy-lip-balm-spf-25?productId=xlsImpprod3730169"},
{"link": "/makeup-remover-cleansing-towelettes?productId=xlsImpprod2940199"},
{"link": "/infallible-paints-eyeshadow-metallics?productId=xlsImpprod16211141"},
{"link": "/rollerwheel-liquid-liner?productId=xlsImpprod16671187"},
{"link": "/vitalist-healthy-elixir-foundation?productId=xlsImpprod16051002"},
{"link": "/curvitude-liner?productId=xlsImpprod16211153"},
{"link": "/colorstay-creme-eyeshadow?productId=xlsImpprod15361017"},
{"link": "/mattifying-powder-foundation?productId=xlsImpprod16781002"},
{"link": "/teint-idole-ultra-wear-camouflage-concealer?productId=xlsImpprod16031105"},
{"link": "/brow-precise-fiber-volumizer?productId=xlsImpprod14371009"},
{"link": "/pop-matte-lip-colour-primer?productId=xlsImpprod14661015"},
{"link": "/infallible-paints-eyeliner?productId=xlsImpprod15361129"},
{"link": "/colour-riche-monos-eyeshadow?productId=xlsImpprod13501023"},
{"link": "/away-we-glow-liquid-highlighter?productId=xlsImpprod15361081"},
{"link": "/oh-my-gloss-oil-tint?productId=xlsImpprod16371021"},
{"link": "/pro-contour-brush?productId=xlsImpprod13361067"},
{"link": "/heavenly-luxe-french-boutique-blush-brush-4?productId=xlsImpprod16411301"},
{"link": "/baby-lips-color-balm-crayon?productId=xlsImpprod15361183"},
{"link": "/volum-express-colossal-big-shot-waterproof-mascara?productId=xlsImpprod15361175"},
{"link": "/kind-eyes-eye-makeup-remover-pads?productId=xlsImpprod5110039"},
{"link": "/colorlicious-melting-pout-liquid-lipstick?productId=xlsImpprod16211127"},
{"link": "/nourishing-eyeliner?productId=xlsImpprod16781004"},
{"link": "/outlast-all-day-soft-touch-concealer?productId=xlsImpprod15091011"},
{"link": "/easy-breezy-brow-fill-shape-define-powder-eyebrow-makeup?productId=xlsImpprod15091007"},
{"link": "/eyeliner-pen?productId=xlsImpprod15361009"}
]